__init__.py
sharepoint_upload.py
sharepoint_upload-0.0.1.dist-info/METADATA
sharepoint_upload-0.0.1.dist-info/WHEEL
sharepoint_upload-0.0.1.dist-info/top_level.txt
sharepoint_upload-0.0.1.dist-info/RECORD
