Metadata-Version: 2.1
Name: sharepoint_upload
Version: 0.0.1
Summary: A package to establish a connection to SharePoint site, and upload files through that connection
Author-email: Mo Sijarrey <mo.sijar.inso@gmail.com>
Project-URL: Homepage, https://github.com/mo-sij-inso
Project-URL: INSO, https://ngosafety.org/
Classifier: Programming Language :: Python :: 3
Classifier: Operating System :: OS Independent
Requires-Python: >=3.10
